{"regions":[{"name":"Rural West Virginia","centroid":[38.4758,-80.8408],"ortho_prosthetic_providers":0,"nearest_major_city":"Charleston, WV","distance_km":113,"barriers":["Provider shortage","Rugged terrain","Rural hospital closures"]},{"name":"Eastern Kentucky (Appalachia)","centroid":[37.5170,-82.8060],"ortho_prosthetic_providers":0,"nearest_major_city":"Lexington, KY","distance_km":161,"barriers":["Mountain isolation","Sparse road network","Limited diagnostic access"],"community_org":"Foundation for Appalachian Kentucky (Hazard)"},{"name":"Mississippi Delta","centroid":[33.4,-90.2],"ortho_prosthetic_providers":0,"nearest_major_city":"Memphis, TN","distance_km":161,"barriers":["Flat delta distances","Limited specialty care","High poverty rates"]}]}